cmat/__init__.py
cmat/base.py
cmat/constant.py
cmat/singlefit.py
cmat/ttv_sim.py
cmat/utils.py
CMAT_astro-0.0.1.dist-info/LICENSE
CMAT_astro-0.0.1.dist-info/METADATA
CMAT_astro-0.0.1.dist-info/WHEEL
CMAT_astro-0.0.1.dist-info/top_level.txt
CMAT_astro-0.0.1.dist-info/RECORD
