Metadata-Version: 2.1
Name: CMAT-astro
Version: 0.0.1
Summary: Companion MAss from Ttv modeling:
Home-page: https://github.com/troyzx/CMAT
Author: Zhang Zixin
Author-email: troyzx@icloud.com
Classifier: Programming Language :: Python :: 3
Classifier: License :: OSI Approved :: MIT License
Classifier: Operating System :: OS Independent
License-File: LICENSE
